License.txt
MANIFEST.in
README.md
RUNME.py
packaging.txt
requirements.txt
setup.py
imvickykumar999.egg-info/PKG-INFO
imvickykumar999.egg-info/SOURCES.txt
imvickykumar999.egg-info/dependency_links.txt
imvickykumar999.egg-info/top_level.txt
multivicks/__init__.py
multivicks/github.py
multivicks/morse.py
multivicks/playfair.py
multivicks/pypi.py
multivicks/vixtor.py
vicksbase/__init__.py
vicksbase/async_fb.py
vicksbase/decorators.py
vicksbase/firebase.py
vicksbase/firebase_token_generator.py
vicksbase/jsonutil.py
vicksbase/lazy.py