Metadata-Version: 1.0
Name: imvickykumar999
Version: 0.0.1
Summary: Website : https://github.com/imvickykumar999/Firebase-CRUD/tree/main/imvickykumar999
Home-page: https://imvickykumar999.herokuapp.com/news
Author: Vicky Kumar
Author-email: UNKNOWN
License: MIT
Keywords: Firebase,Playfair Cipher,GitHub Uploader,Morse,custom,python package,function and class,3D line,3D plane,angle bw planes or line,distance bw point and plane
Platform: UNKNOWN
